vcspack200/__init__.py
vcspack200/utils.py
vcspack200-0.1.dist-info/LICENSE.txt
vcspack200-0.1.dist-info/METADATA
vcspack200-0.1.dist-info/WHEEL
vcspack200-0.1.dist-info/top_level.txt
vcspack200-0.1.dist-info/RECORD
